kd_weather
